cloudomate/__init__.py
cloudomate/cmdline.py
cloudomate/globals.py
cloudomate/wallet.py
cloudomate/exceptions/__init__.py
cloudomate/exceptions/vps_out_of_stock.py
cloudomate/gateway/__init__.py
cloudomate/gateway/bitpay.py
cloudomate/gateway/blockchain.py
cloudomate/gateway/coinbase.py
cloudomate/gateway/gateway.py
cloudomate/gateway/undergroundprivate.py
cloudomate/hoster/__init__.py
cloudomate/hoster/hoster.py
cloudomate/hoster/vpn/__init__.py
cloudomate/hoster/vpn/azirevpn.py
cloudomate/hoster/vpn/vpn_hoster.py
cloudomate/hoster/vps/__init__.py
cloudomate/hoster/vps/blueangelhost.py
cloudomate/hoster/vps/ccihosting.py
cloudomate/hoster/vps/clientarea.py
cloudomate/hoster/vps/crowncloud.py
cloudomate/hoster/vps/linevast.py
cloudomate/hoster/vps/proxhost.py
cloudomate/hoster/vps/pulseservers.py
cloudomate/hoster/vps/solusvm_hoster.py
cloudomate/hoster/vps/twosync.py
cloudomate/hoster/vps/undergroundprivate.py
cloudomate/hoster/vps/vps_hoster.py
cloudomate/test/__init__.py
cloudomate/test/test_captchasolver.py
cloudomate/test/test_clientarea.py
cloudomate/test/test_cmdline.py
cloudomate/test/test_gateway.py
cloudomate/test/test_hoster.py
cloudomate/test/test_settings.py
cloudomate/test/test_vpn_hosters.py
cloudomate/test/test_vps_hosters.py
cloudomate/util/__init__.py
cloudomate/util/bitcoinaddress.py
cloudomate/util/captchasolver.py
cloudomate/util/fakeuserscraper.py
cloudomate/util/settings.py
cloudomate-1.4.dist-info/METADATA
cloudomate-1.4.dist-info/RECORD
cloudomate-1.4.dist-info/WHEEL
cloudomate-1.4.dist-info/entry_points.txt
cloudomate-1.4.dist-info/top_level.txt
