Metadata-Version: 2.1
Name: cloudomate
Version: 1.4
Summary: Automate buying VPS instances with Bitcoin
Home-page: https://github.com/tribler/cloudomate
Author: PlebNet
Author-email: authentic8989@gmail.com
License: LGPLv3
Keywords: vps bitcoin
Platform: UNKNOWN
Classifier: Development Status :: 3 - Alpha
Classifier: Intended Audience :: Developers
Classifier: Topic :: System :: Installation/Setup
Classifier: Topic :: Software Development :: Libraries :: Python Modules
Classifier: License :: OSI Approved :: GNU Lesser General Public License v3 (LGPLv3)
Classifier: Programming Language :: Python :: 3
Classifier: Programming Language :: Python :: 3.6
Classifier: Operating System :: POSIX :: Linux
Classifier: Operating System :: MacOS
Provides-Extra: test
Provides-Extra: dev
Requires-Dist: appdirs
Requires-Dist: lxml
Requires-Dist: MechanicalSoup
Requires-Dist: CurrencyConverter
Requires-Dist: bs4
Requires-Dist: forex-python
Requires-Dist: parameterized
Requires-Dist: fake-useragent
Requires-Dist: CaseInsensitiveDict
Requires-Dist: ConfigParser
Requires-Dist: future
Requires-Dist: requests[security]
Provides-Extra: dev
Provides-Extra: test
Requires-Dist: mock; extra == 'test'
Requires-Dist: parameterized; extra == 'test'
